pyclnf
