Metadata-Version: 2.4
Name: pyclnf
Version: 0.3.2
Summary: Pure Python implementation of CLNF (Constrained Local Neural Fields) facial landmark detector
Author-email: John Wilson IV <your.email@example.com>
License: CC BY-NC 4.0
Project-URL: Homepage, https://github.com/johnwilsoniv/pyclnf
Project-URL: Repository, https://github.com/johnwilsoniv/pyclnf
Project-URL: Bug Tracker, https://github.com/johnwilsoniv/pyclnf/issues
Keywords: clnf,facial-landmarks,face-alignment,openface,computer-vision,pure-python,mtcnn
Classifier: Development Status :: 4 - Beta
Classifier: Intended Audience :: Developers
Classifier: Intended Audience :: Science/Research
Classifier: License :: Other/Proprietary License
Classifier: Programming Language :: Python :: 3
Classifier: Programming Language :: Python :: 3.8
Classifier: Programming Language :: Python :: 3.9
Classifier: Programming Language :: Python :: 3.10
Classifier: Programming Language :: Python :: 3.11
Classifier: Programming Language :: Python :: 3.12
Classifier: Topic :: Scientific/Engineering :: Artificial Intelligence
Classifier: Topic :: Scientific/Engineering :: Image Recognition
Requires-Python: >=3.8
License-File: LICENSE
Requires-Dist: numpy>=1.19.0
Requires-Dist: opencv-python>=4.5.0
Requires-Dist: pymtcnn>=1.0.0
Provides-Extra: dev
Requires-Dist: pytest>=7.0.0; extra == "dev"
Requires-Dist: pytest-cov>=3.0.0; extra == "dev"
Requires-Dist: black>=22.0.0; extra == "dev"
Requires-Dist: flake8>=4.0.0; extra == "dev"
Dynamic: license-file
